<?xml version="1.0" ?>
<DataDicTable>
<class>com.egen.tool.datadic.DataDicTable</class>
<componentDescription></componentDescription>
<componentName>tb_turma</componentName>
<lastChange>1430853504688</lastChange>
<dataDicTableConstraintPk><class>com.egen.tool.datadic.DataDicTableConstraintPk</class>
<constraintName>pk_tb_turma</constraintName>
<constraintDescription></constraintDescription>
<lastChange>0</lastChange>
<referencedColumnReferences>
<referencedColumnReferences_item>
<class>java.lang.String</class>
<value>id_turma</value>
</referencedColumnReferences_item>
</referencedColumnReferences>
<dataDicTableConstraintSetProperties>
</dataDicTableConstraintSetProperties>
</dataDicTableConstraintPk>
<dataDicTableColumns>
<dataDicTableColumns_item>
<class>com.egen.tool.datadic.DataDicTableColumn</class>
<columnSize>0</columnSize>
<dataDicTableColumnDomainReference></dataDicTableColumnDomainReference>
<columnType>INT</columnType>
<columnScale>0</columnScale>
<columnNotnull>true</columnNotnull>
<columnDescription></columnDescription>
<columnName>id_turma</columnName>
<columnIsAutoIncrement>false</columnIsAutoIncrement>
<columnDefaultValue></columnDefaultValue>
<lastChange>0</lastChange>
<dataDicTableColumnSetProperties>
</dataDicTableColumnSetProperties>
</dataDicTableColumns_item>
<dataDicTableColumns_item>
<class>com.egen.tool.datadic.DataDicTableColumn</class>
<columnSize>3</columnSize>
<dataDicTableColumnDomainReference></dataDicTableColumnDomainReference>
<columnType>VARCHAR()</columnType>
<columnScale>0</columnScale>
<columnNotnull>true</columnNotnull>
<columnDescription></columnDescription>
<columnName>nm_turma</columnName>
<columnIsAutoIncrement>false</columnIsAutoIncrement>
<columnDefaultValue></columnDefaultValue>
<lastChange>0</lastChange>
<dataDicTableColumnSetProperties>
</dataDicTableColumnSetProperties>
</dataDicTableColumns_item>
</dataDicTableColumns>
<dataDicTableTriggers>
</dataDicTableTriggers>
<dataDicTableIndexes>
</dataDicTableIndexes>
<dataDicTableConstraintUks>
</dataDicTableConstraintUks>
<dataDicTableConstraintFks>
</dataDicTableConstraintFks>
<dataDicTableConstraintChecks>
</dataDicTableConstraintChecks>
<dataDicGrants>
</dataDicGrants>
<dataDicComponentSetProperties>
</dataDicComponentSetProperties>
</DataDicTable>
